{
  "mineMissions": [
    "For a Few Darkstone More",
    "Exploration",
    "Rescue Party",
    "Seal the Gate",
    "Blow the Mine",
    "Escape"
  ],
  "canyonMissions": [
    "Canyon Missing Patrol",
    "Canyon Ghosts in the Dark"
  ],
  "cynderMissions": [
    "Cracks in Reality",
    "Defend the Bridge",
    "Dark Deal",
    "Fire & Ash",
    "Hunt for Liquid DS",
    "Broken Seals"
  ],
  "targaMissions": [
    "Terror in the Night",
    "Stop the Ritual",
    "Last Stand",
    "Overload",
    "City of the Ancients",
    "Frozen Expedition"
  ],
  "jargonoMissions": [
    "Night of the Dead",
    "Seal the Hell Pit",
    "The Lost Journal",
    "Cursed Idol",
    "Swamps of Death",
    "Temple of Dread"
  ],
  "derelictMissions": [
    "Time's Echo",
    "Collapse the Vortex",
    "Lost in Space",
    "The Captain's Log",
    "Voyage of the Dead",
    "Reactor Breach"
  ],
  "trederraMissions": [
    "Foothold",
    "Toxic Purge",
    "Battlefield Recon",
    "Front Lines",
    "Guns of War",
    "Doomsday"
  ],
  "blastedMissions": [
    "Across the Desert Dunes",
    "Starfall",
    "Water of Life",
    "Warmaster's Fury"
  ],
  "townMissions": [
    "Shootout in the Streets",
    "Hanging High",
    "Bank Robbery",
    "Jail Break",
    "Town Overrun",
    "High Noon Duel"
  ],
  "bellyMissions": [
    "A Living World",
    "Devoured by the Beast",
    "If it Bleeds",
    "Beast Beneath the World",
    "Ancient Hunger"
  ],
  "fortressMissions": [
    "Hunt for Dark Stone",
    "Exploration",
    "Seal the Void Gate",
    "Search Party",
    "Escape",
    "Bring Down the Fortress",
    "Cursed Temple",
    "Sacred Relic",
    "Enemy at the Gates",
    "Power of the Shogun",
    "Castle of the Dead",
    "The Sorcerer’s Library",
    "Lost Explorer"
  ],
  "forestMissions": [
    "A Haunting",
    "Overgrown",
    "Into the Shadow Realm",
    "Specters of the Past",
    "Broken Amulet",
    "Once a Hero"
  ]
}
